<?xml version="1.0" encoding="UTF-8"?>

<residentialEv>
    <pluginProbability>
        <means>
            <mean>15.551363809411892</mean>
            <mean>14.906364879495973</mean>
            <mean>18.810023204437442</mean>
            <mean>18.42721969895118</mean>
            <mean>11.511281432747051</mean>
        </means>
        <covs>
            <cov>11.40013254836173</cov>
            <cov>9.087142339348768</cov>
            <cov>6.025711816195868</cov>
            <cov>8.178929231596902</cov>
            <cov>47.44475519805955</cov>
        </covs>
        <weights>0.14041109169727997,0.27587634415754236,0.2217500910448088,0.24352078840880703,0.11844168469156201</weights>
    </pluginProbability>
    <instances>hod0,hod1,hod2,hod3,hod4,hod5,hod6,hod7,hod8,hod9,hod10,hod11,hod12,hod13,hod14,hod15,hod16,hod17,hod18,hod19,hod20,hod21,hod22,hod23</instances>
    <hod0>
        <means>
            <mean>1.2341130665677,4.398720283675276</mean>
            <mean>4.170944656713521,7.889116710127824</mean>
            <mean>30.828161632121493,16.03812471422226</mean>
            <mean>34.670273435362404,1.8944353285895232</mean>
            <mean>8.880749018427318,14.438422390356903</mean>
        </means>
        <covs>
            <cov>0.7855770791643906,2.828040806226375,2.828040806226375,10.190183631388722</cov>
            <cov>2.346844783071306,4.058463749289235,4.058463749289235,45.270418489071936</cov>
            <cov>0.4251155624521177,0.2461908003864992,0.24619080038649888,104.26136590956698</cov>
            <cov>10.50942442567346,-0.3577289658152334,-0.3577289658152334,31.96020322134531</cov>
            <cov>154.4086470860663,-79.65341706157162,-79.65341706157162,136.1101862088604</cov>
        </covs>
        <weights>0.00024168612854922806,0.0001053681274959851,3.770078044104136e-12,1.9313376201497643e-08,0.9996529264268085</weights>
    </hod0>
    <hod1>
        <means>
            <mean>1.2295889952440022,4.383160571580407</mean>
            <mean>4.097968757889284,8.035242488138973</mean>
            <mean>29.83656967631486,15.974051011570984</mean>
            <mean>33.672133286279404,2.3504030538869003</mean>
            <mean>9.975554062332593,14.802099368776087</mean>
        </means>
        <covs>
            <cov>0.7855770791643906,2.828040806226375,2.828040806226375,10.190183631388722</cov>
            <cov>2.346844783071306,4.058463749289235,4.058463749289235,45.270418489071936</cov>
            <cov>0.4251155624521177,0.2461908003864992,0.24619080038649888,104.26136590956698</cov>
            <cov>10.50942442567346,-0.3577289658152334,-0.3577289658152334,31.96020322134531</cov>
            <cov>154.4086470860663,-79.65341706157162,-79.65341706157162,136.1101862088604</cov>
        </covs>
        <weights>0.0007169851655084554,0.00040746406645412325,6.235726853650684e-11,1.3697686294426335e-07,0.9988754137288172</weights>
    </hod1>
    <hod2>
        <means>
            <mean>1.2250649239203042,4.367600859485538</mean>
            <mean>4.024992859065045,8.181368266150121</mean>
            <mean>28.84497772050822,15.909977308919709</mean>
            <mean>32.6739931371964,2.8063707791842765</mean>
            <mean>11.070359106237868,15.165776347195271</mean>
        </means>
        <covs>
            <cov>0.7855770791643906,2.828040806226375,2.828040806226375,10.190183631388722</cov>
            <cov>2.346844783071306,4.058463749289235,4.058463749289235,45.270418489071936</cov>
            <cov>0.4251155624521177,0.2461908003864992,0.24619080038649888,104.26136590956698</cov>
            <cov>10.50942442567346,-0.3577289658152334,-0.3577289658152334,31.96020322134531</cov>
            <cov>154.4086470860663,-79.65341706157162,-79.65341706157162,136.1101862088604</cov>
        </covs>
        <weights>0.001986837835047198,0.0014393504341045527,8.909219110479869e-10,8.766503614787189e-07,0.9965729341895648</weights>
    </hod2>
    <hod3>
        <means>
            <mean>1.2205408525966062,4.352041147390669</mean>
            <mean>3.952016960240807,8.32749404416127</mean>
            <mean>27.853385764701585,15.845903606268433</mean>
            <mean>31.675852988113398,3.2623385044816526</mean>
            <mean>12.165164150143143,15.529453325614455</mean>
        </means>
        <covs>
            <cov>0.7855770791643906,2.828040806226375,2.828040806226375,10.190183631388722</cov>
            <cov>2.346844783071306,4.058463749289235,4.058463749289235,45.270418489071936</cov>
            <cov>0.4251155624521177,0.2461908003864992,0.24619080038649888,104.26136590956698</cov>
            <cov>10.50942442567346,-0.3577289658152334,-0.3577289658152334,31.96020322134531</cov>
            <cov>154.4086470860663,-79.65341706157162,-79.65341706157162,136.1101862088604</cov>
        </covs>
        <weights>0.005129831185532841,0.004632714538561109,1.0967372760283599e-08,5.049988575732617e-06,0.9902323933199576</weights>
    </hod3>
    <hod4>
        <means>
            <mean>1.2160167812729084,4.336481435295801</mean>
            <mean>3.8790410614165687,8.473619822172418</mean>
            <mean>26.86179380889495,15.781829903617158</mean>
            <mean>30.6777128390304,3.718306229779029</mean>
            <mean>13.259969194048418,15.893130304033638</mean>
        </means>
        <covs>
            <cov>0.7855770791643906,2.828040806226375,2.828040806226375,10.190183631388722</cov>
            <cov>2.346844783071306,4.058463749289235,4.058463749289235,45.270418489071936</cov>
            <cov>0.4251155624521177,0.2461908003864992,0.24619080038649888,104.26136590956698</cov>
            <cov>10.50942442567346,-0.3577289658152334,-0.3577289658152334,31.96020322134531</cov>
            <cov>154.4086470860663,-79.65341706157162,-79.65341706157162,136.1101862088604</cov>
        </covs>
        <weights>0.012268297651088757,0.013506676108533712,1.1564534491538602e-07,2.6031028797144626e-05,0.9741988795662355</weights>
    </hod4>
    <hod5>
        <means>
            <mean>1.2114927099492103,4.320921723200932</mean>
            <mean>3.8060651625923305,8.619745600183569</mean>
            <mean>25.870201853088318,15.717756200965884</mean>
            <mean>29.6795726899474,4.174273955076405</mean>
            <mean>14.354774237953695,16.256807282452822</mean>
        </means>
        <covs>
            <cov>0.7855770791643906,2.828040806226375,2.828040806226375,10.190183631388722</cov>
            <cov>2.346844783071306,4.058463749289235,4.058463749289235,45.270418489071936</cov>
            <cov>0.4251155624521177,0.2461908003864992,0.24619080038649888,104.26136590956698</cov>
            <cov>10.50942442567346,-0.3577289658152334,-0.3577289658152334,31.96020322134531</cov>
            <cov>154.4086470860663,-79.65341706157162,-79.65341706157162,136.1101862088604</cov>
        </covs>
        <weights>0.026857347720821958,0.035250265030957524,1.032222452728018e-06,0.00011865505231686131,0.9377726999734509</weights>
    </hod5>
    <hod6>
        <means>
            <mean>1.2069686386255125,4.305362011106063</mean>
            <mean>3.7330892637680924,8.765871378194717</mean>
            <mean>24.878609897281684,15.653682498314609</mean>
            <mean>28.6814325408644,4.630241680373781</mean>
            <mean>15.44957928185897,16.620484260872008</mean>
        </means>
        <covs>
            <cov>0.7855770791643906,2.828040806226375,2.828040806226375,10.190183631388722</cov>
            <cov>2.346844783071306,4.058463749289235,4.058463749289235,45.270418489071936</cov>
            <cov>0.4251155624521177,0.2461908003864992,0.24619080038649888,104.26136590956698</cov>
            <cov>10.50942442567346,-0.3577289658152334,-0.3577289658152334,31.96020322134531</cov>
            <cov>154.4086470860663,-79.65341706157162,-79.65341706157162,136.1101862088604</cov>
        </covs>
        <weights>0.05276859806812993,0.08074456012457477,7.646700340146835e-06,0.00046893336329122847,0.8660102617436639</weights>
    </hod6>
    <hod7>
        <means>
            <mean>1.2024445673018145,4.289802299011194</mean>
            <mean>3.6601133649438538,8.911997156205866</mean>
            <mean>23.88701794147505,15.589608795663333</mean>
            <mean>27.6832923917814,5.086209405671157</mean>
            <mean>16.544384325764245,16.98416123929119</mean>
        </means>
        <covs>
            <cov>0.7855770791643906,2.828040806226375,2.828040806226375,10.190183631388722</cov>
            <cov>2.346844783071306,4.058463749289235,4.058463749289235,45.270418489071936</cov>
            <cov>0.4251155624521177,0.2461908003864992,0.24619080038649888,104.26136590956698</cov>
            <cov>10.50942442567346,-0.3577289658152334,-0.3577289658152334,31.96020322134531</cov>
            <cov>154.4086470860663,-79.65341706157162,-79.65341706157162,136.1101862088604</cov>
        </covs>
        <weights>0.09084690049196362,0.15848554311247692,4.590066451935187e-05,0.0015687528688239447,0.7490529028622162</weights>
    </hod7>
    <hod8>
        <means>
            <mean>1.1979204959781167,4.274242586916325</mean>
            <mean>3.587137466119616,9.058122934217014</mean>
            <mean>22.895425985668417,15.525535093012058</mean>
            <mean>26.6851522426984,5.5421771309685335</mean>
            <mean>17.63918936966952,17.347838217710375</mean>
        </means>
        <covs>
            <cov>0.7855770791643906,2.828040806226375,2.828040806226375,10.190183631388722</cov>
            <cov>2.346844783071306,4.058463749289235,4.058463749289235,45.270418489071936</cov>
            <cov>0.4251155624521177,0.2461908003864992,0.24619080038649888,104.26136590956698</cov>
            <cov>10.50942442567346,-0.3577289658152334,-0.3577289658152334,31.96020322134531</cov>
            <cov>154.4086470860663,-79.65341706157162,-79.65341706157162,136.1101862088604</cov>
        </covs>
        <weights>0.1350077720171054,0.2625932135762256,0.0002199378521112834,0.004376313336193697,0.5978027632183641</weights>
    </hod8>
    <hod9>
        <means>
            <mean>1.1933964246544186,4.2586828748214565</mean>
            <mean>3.5141615672953774,9.204248712228164</mean>
            <mean>21.903834029861784,15.461461390360782</mean>
            <mean>25.6870120936154,5.99814485626591</mean>
            <mean>18.733994413574795,17.711515196129557</mean>
        </means>
        <covs>
            <cov>0.7855770791643906,2.828040806226375,2.828040806226375,10.190183631388722</cov>
            <cov>2.346844783071306,4.058463749289235,4.058463749289235,45.270418489071936</cov>
            <cov>0.4251155624521177,0.2461908003864992,0.24619080038649888,104.26136590956698</cov>
            <cov>10.50942442567346,-0.3577289658152334,-0.3577289658152334,31.96020322134531</cov>
            <cov>154.4086470860663,-79.65341706157162,-79.65341706157162,136.1101862088604</cov>
        </covs>
        <weights>0.17463923193086112,0.3703523452915635,0.0008482763914035805,0.010265805944919862,0.4438943404412519</weights>
    </hod9>
    <hod10>
        <means>
            <mean>1.1888723533307206,4.2431231627265875</mean>
            <mean>3.4411856684711393,9.350374490239313</mean>
            <mean>20.91224207405515,15.397387687709507</mean>
            <mean>24.688871944532398,6.454112581563286</mean>
            <mean>19.82879945748007,18.075192174548743</mean>
        </means>
        <covs>
            <cov>0.7855770791643906,2.828040806226375,2.828040806226375,10.190183631388722</cov>
            <cov>2.346844783071306,4.058463749289235,4.058463749289235,45.270418489071936</cov>
            <cov>0.4251155624521177,0.2461908003864992,0.24619080038649888,104.26136590956698</cov>
            <cov>10.50942442567346,-0.3577289658152334,-0.3577289658152334,31.96020322134531</cov>
            <cov>154.4086470860663,-79.65341706157162,-79.65341706157162,136.1101862088604</cov>
        </covs>
        <weights>0.2025472923104671,0.4579854238546563,0.002712678812841671,0.020858143801471312,0.31589646122056364</weights>
    </hod10>
    <hod11>
        <means>
            <mean>1.1843482820070228,4.2275634506317195</mean>
            <mean>3.368209769646901,9.496500268250461</mean>
            <mean>19.920650118248513,15.333313985058233</mean>
            <mean>23.6907317954494,6.910080306860662</mean>
            <mean>20.923604501385345,18.438869152967925</mean>
        </means>
        <covs>
            <cov>0.7855770791643906,2.828040806226375,2.828040806226375,10.190183631388722</cov>
            <cov>2.346844783071306,4.058463749289235,4.058463749289235,45.270418489071936</cov>
            <cov>0.4251155624521177,0.2461908003864992,0.24619080038649888,104.26136590956698</cov>
            <cov>10.50942442567346,-0.3577289658152334,-0.3577289658152334,31.96020322134531</cov>
            <cov>154.4086470860663,-79.65341706157162,-79.65341706157162,136.1101862088604</cov>
        </covs>
        <weights>0.21791235401204348,0.5137624544971005,0.007441357325650742,0.03797741704950803,0.22290641711569736</weights>
    </hod11>
    <hod12>
        <means>
            <mean>1.1798242106833248,4.2120037385368505</mean>
            <mean>3.295233870822663,9.64262604626161</mean>
            <mean>18.92905816244188,15.269240282406956</mean>
            <mean>22.6925916463664,7.366048032158038</mean>
            <mean>22.01840954529062,18.80254613138711</mean>
        </means>
        <covs>
            <cov>0.7855770791643906,2.828040806226375,2.828040806226375,10.190183631388722</cov>
            <cov>2.346844783071306,4.058463749289235,4.058463749289235,45.270418489071936</cov>
            <cov>0.4251155624521177,0.2461908003864992,0.24619080038649888,104.26136590956698</cov>
            <cov>10.50942442567346,-0.3577289658152334,-0.3577289658152334,31.96020322134531</cov>
            <cov>154.4086470860663,-79.65341706157162,-79.65341706157162,136.1101862088604</cov>
        </covs>
        <weights>0.22288528835207644,0.535822047963627,0.017946182999004072,0.06350613904854849,0.15984034163674402</weights>
    </hod12>
    <hod13>
        <means>
            <mean>1.175300139359627,4.196444026441982</mean>
            <mean>3.222257971998425,9.78875182427276</mean>
            <mean>17.937466206635246,15.205166579755682</mean>
            <mean>21.6944514972834,7.822015757455414</mean>
            <mean>23.113214589195895,19.166223109806293</mean>
        </means>
        <covs>
            <cov>0.7855770791643906,2.828040806226375,2.828040806226375,10.190183631388722</cov>
            <cov>2.346844783071306,4.058463749289235,4.058463749289235,45.270418489071936</cov>
            <cov>0.4251155624521177,0.2461908003864992,0.24619080038649888,104.26136590956698</cov>
            <cov>10.50942442567346,-0.3577289658152334,-0.3577289658152334,31.96020322134531</cov>
            <cov>154.4086470860663,-79.65341706157162,-79.65341706157162,136.1101862088604</cov>
        </covs>
        <weights>0.2192899708304722,0.525678216231097,0.03849921257462846,0.09868251048710092,0.11785008987670136</weights>
    </hod13>
    <hod14>
        <means>
            <mean>1.170776068035929,4.180884314347113</mean>
            <mean>3.149282073174186,9.934877602283908</mean>
            <mean>16.94587425082861,15.141092877104407</mean>
            <mean>20.696311348200396,8.277983482752791</mean>
            <mean>24.20801963310117,19.529900088225478</mean>
        </means>
        <covs>
            <cov>0.7855770791643906,2.828040806226375,2.828040806226375,10.190183631388722</cov>
            <cov>2.346844783071306,4.058463749289235,4.058463749289235,45.270418489071936</cov>
            <cov>0.4251155624521177,0.2461908003864992,0.24619080038649888,104.26136590956698</cov>
            <cov>10.50942442567346,-0.3577289658152334,-0.3577289658152334,31.96020322134531</cov>
            <cov>154.4086470860663,-79.65341706157162,-79.65341706157162,136.1101862088604</cov>
        </covs>
        <weights>0.2079579739425926,0.4861185475214601,0.07361614158598224,0.1427843106428196,0.08952302630714533</weights>
    </hod14>
    <hod15>
        <means>
            <mean>1.1662519967122311,4.165324602252244</mean>
            <mean>3.076306174349948,10.081003380295057</mean>
            <mean>15.954282295021978,15.077019174453131</mean>
            <mean>19.698171199117397,8.733951208050167</mean>
            <mean>25.302824677006445,19.89357706664466</mean>
        </means>
        <covs>
            <cov>0.7855770791643906,2.828040806226375,2.828040806226375,10.190183631388722</cov>
            <cov>2.346844783071306,4.058463749289235,4.058463749289235,45.270418489071936</cov>
            <cov>0.4251155624521177,0.2461908003864992,0.24619080038649888,104.26136590956698</cov>
            <cov>10.50942442567346,-0.3577289658152334,-0.3577289658152334,31.96020322134531</cov>
            <cov>154.4086470860663,-79.65341706157162,-79.65341706157162,136.1101862088604</cov>
        </covs>
        <weights>0.18976069165645246,0.42300124029919794,0.12525357553398095,0.19203970784467883,0.0699447846656898</weights>
    </hod15>
    <hod16>
        <means>
            <mean>1.161727925388533,4.149764890157375</mean>
            <mean>3.00333027552571,10.227129158306205</mean>
            <mean>14.962690339215342,15.012945471801856</mean>
            <mean>18.700031050034397,9.189918933347542</mean>
            <mean>26.39762972091172,20.257254045063846</mean>
        </means>
        <covs>
            <cov>0.7855770791643906,2.828040806226375,2.828040806226375,10.190183631388722</cov>
            <cov>2.346844783071306,4.058463749289235,4.058463749289235,45.270418489071936</cov>
            <cov>0.4251155624521177,0.2461908003864992,0.24619080038649888,104.26136590956698</cov>
            <cov>10.50942442567346,-0.3577289658152334,-0.3577289658152334,31.96020322134531</cov>
            <cov>154.4086470860663,-79.65341706157162,-79.65341706157162,136.1101862088604</cov>
        </covs>
        <weights>0.16679880952916132,0.34673722879299623,0.1898389118688361,0.2403554519624927,0.05626959784651358</weights>
    </hod16>
    <hod17>
        <means>
            <mean>1.157203854064835,4.134205178062507</mean>
            <mean>2.9303543767014717,10.373254936317355</mean>
            <mean>13.971098383408709,14.948871769150582</mean>
            <mean>17.701890900951398,9.645886658644919</mean>
            <mean>27.492434764817,20.620931023483028</mean>
        </means>
        <covs>
            <cov>0.7855770791643906,2.828040806226375,2.828040806226375,10.190183631388722</cov>
            <cov>2.346844783071306,4.058463749289235,4.058463749289235,45.270418489071936</cov>
            <cov>0.4251155624521177,0.2461908003864992,0.24619080038649888,104.26136590956698</cov>
            <cov>10.50942442567346,-0.3577289658152334,-0.3577289658152334,31.96020322134531</cov>
            <cov>154.4086470860663,-79.65341706157162,-79.65341706157162,136.1101862088604</cov>
        </covs>
        <weights>0.14239535327466052,0.2699472170140677,0.2584154799700245,0.28224709190737773,0.046994857833869606</weights>
    </hod17>
    <hod18>
        <means>
            <mean>1.1526797827411372,4.118645465967638</mean>
            <mean>2.8573784778772335,10.519380714328504</mean>
            <mean>12.979506427602075,14.884798066499306</mean>
            <mean>16.703750751868398,10.101854383942296</mean>
            <mean>28.587239808722273,20.984608001902213</mean>
        </means>
        <covs>
            <cov>0.7855770791643906,2.828040806226375,2.828040806226375,10.190183631388722</cov>
            <cov>2.346844783071306,4.058463749289235,4.058463749289235,45.270418489071936</cov>
            <cov>0.4251155624521177,0.2461908003864992,0.24619080038649888,104.26136590956698</cov>
            <cov>10.50942442567346,-0.3577289658152334,-0.3577289658152334,31.96020322134531</cov>
            <cov>154.4086470860663,-79.65341706157162,-79.65341706157162,136.1101862088604</cov>
        </covs>
        <weights>0.1198228329760313,0.20258230085666423,0.3206377990004415,0.3156038177678144,0.041353249399048664</weights>
    </hod18>
    <hod19>
        <means>
            <mean>1.1481557114174392,4.103085753872769</mean>
            <mean>2.7844025790529954,10.665506492339652</mean>
            <mean>11.98791447179544,14.820724363848031</mean>
            <mean>15.705610602785399,10.557822109239671</mean>
            <mean>29.68204485262755,21.348284980321395</mean>
        </means>
        <covs>
            <cov>0.7855770791643906,2.828040806226375,2.828040806226375,10.190183631388722</cov>
            <cov>2.346844783071306,4.058463749289235,4.058463749289235,45.270418489071936</cov>
            <cov>0.4251155624521177,0.2461908003864992,0.24619080038649888,104.26136590956698</cov>
            <cov>10.50942442567346,-0.3577289658152334,-0.3577289658152334,31.96020322134531</cov>
            <cov>154.4086470860663,-79.65341706157162,-79.65341706157162,136.1101862088604</cov>
        </covs>
        <weights>0.10110977024601503,0.14908614572627285,0.3689289137992968,0.34187014244891073,0.03900502777950469</weights>
    </hod19>
    <hod20>
        <means>
            <mean>1.1436316400937414,4.0875260417779</mean>
            <mean>2.711426680228757,10.8116322703508</mean>
            <mean>10.996322515988807,14.756650661196757</mean>
            <mean>14.707470453702397,11.013789834537047</mean>
            <mean>30.776849896532823,21.71196195874058</mean>
        </means>
        <covs>
            <cov>0.7855770791643906,2.828040806226375,2.828040806226375,10.190183631388722</cov>
            <cov>2.346844783071306,4.058463749289235,4.058463749289235,45.270418489071936</cov>
            <cov>0.4251155624521177,0.2461908003864992,0.24619080038649888,104.26136590956698</cov>
            <cov>10.50942442567346,-0.3577289658152334,-0.3577289658152334,31.96020322134531</cov>
            <cov>154.4086470860663,-79.65341706157162,-79.65341706157162,136.1101862088604</cov>
        </covs>
        <weights>0.08686236111025981,0.10923489877475463,0.3996479981955468,0.364218031632511,0.04003671028692787</weights>
    </hod20>
    <hod21>
        <means>
            <mean>1.1391075687700434,4.071966329683031</mean>
            <mean>2.6384507814045186,10.957758048361951</mean>
            <mean>10.004730560182171,14.69257695854548</mean>
            <mean>13.709330304619398,11.469757559834424</mean>
            <mean>31.8716549404381,22.075638937159766</mean>
        </means>
        <covs>
            <cov>0.7855770791643906,2.828040806226375,2.828040806226375,10.190183631388722</cov>
            <cov>2.346844783071306,4.058463749289235,4.058463749289235,45.270418489071936</cov>
            <cov>0.4251155624521177,0.2461908003864992,0.24619080038649888,104.26136590956698</cov>
            <cov>10.50942442567346,-0.3577289658152334,-0.3577289658152334,31.96020322134531</cov>
            <cov>154.4086470860663,-79.65341706157162,-79.65341706157162,136.1101862088604</cov>
        </covs>
        <weights>0.07677101640244566,0.08052227865444116,0.41187150982495874,0.3856428155795662,0.0451923795385881</weights>
    </hod21>
    <hod22>
        <means>
            <mean>1.1345834974463456,4.056406617588162</mean>
            <mean>2.5654748825802804,11.1038838263731</mean>
            <mean>9.013138604375538,14.628503255894206</mean>
            <mean>12.711190155536398,11.9257252851318</mean>
            <mean>32.96645998434337,22.43931591557895</mean>
        </means>
        <covs>
            <cov>0.7855770791643906,2.828040806226375,2.828040806226375,10.190183631388722</cov>
            <cov>2.346844783071306,4.058463749289235,4.058463749289235,45.270418489071936</cov>
            <cov>0.4251155624521177,0.2461908003864992,0.24619080038649888,104.26136590956698</cov>
            <cov>10.50942442567346,-0.3577289658152334,-0.3577289658152334,31.96020322134531</cov>
            <cov>154.4086470860663,-79.65341706157162,-79.65341706157162,136.1101862088604</cov>
        </covs>
        <weights>0.07013759954854538,0.06000148766258792,0.40574746641698295,0.4077494398392832,0.056364006532600715</weights>
    </hod22>
    <hod23>
        <means>
            <mean>1.1300594261226475,4.040846905493293</mean>
            <mean>2.4924989837560423,11.250009604384248</mean>
            <mean>8.021546648568904,14.564429553242931</mean>
            <mean>11.713050006453397,12.381693010429176</mean>
            <mean>34.06126502824865,22.80299289399813</mean>
        </means>
        <covs>
            <cov>0.7855770791643906,2.828040806226375,2.828040806226375,10.190183631388722</cov>
            <cov>2.346844783071306,4.058463749289235,4.058463749289235,45.270418489071936</cov>
            <cov>0.4251155624521177,0.2461908003864992,0.24619080038649888,104.26136590956698</cov>
            <cov>10.50942442567346,-0.3577289658152334,-0.3577289658152334,31.96020322134531</cov>
            <cov>154.4086470860663,-79.65341706157162,-79.65341706157162,136.1101862088604</cov>
        </covs>
        <weights>0.06612322138527003,0.04511914349977497,0.38143574290297,0.42978116352950596,0.07754072868247908</weights>
    </hod23>
</residentialEv>
